{
	"status": "succeeded",
	"createdDateTime": "2024-06-19T18:26:18Z",
	"lastUpdatedDateTime": "2024-06-19T18:26:19Z",
	"analyzeResult": {
		"apiVersion": "2023-07-31",
		"modelId": "prebuilt-layout",
		"stringIndexType": "utf16CodeUnit",
		"content": "NEXGEN\nInnovation drives progress\nPRODUCT ID UNIT PRICE QUANTITY TOTAL PRICE\nINVOICE\nCustomer:\nHessel\nAddress:\n41 Borough Road, Birmingham, B1 5NB\nDelivery Date:\n6/19/2024\nInvoice #:\n4441423\nPurchase Order: 17211\nJB508\n9.50\n2\n19.00\nPL-14X\n5.25\n1\n5.25\nTOTAL\n3\n24.25\nCUSTOMER SIGNATURE:\nNAME: Sarah P\nDRIVER SIGNATURE:\nNAME: James T\nNEXGEN\nInnovation drives progress\nRETURNS\nCustomer:\nHessel\nAddress:\n41 Borough Road, Birmingham, B1 5NB\nDelivery Date:\n6/19/2024\nInvoice #:\n4441423\nPurchase Order: 17211\nPRODUCT ID QUANTITY REASON\nTOTAL\n0\nCUSTOMER SIGNATURE:\nNAME:\nDRIVER SIGNATURE:\nNAME: James T",
		"pages": [
			{
				"pageNumber": 1,
				"angle": 0.14468510448932648,
				"width": 8.5,
				"height": 11,
				"unit": "inch",
				"words": [
					{
						"content": "NEXGEN",
						"polygon": [
							1.0697,
							1.2127,
							1.9435,
							1.2079,
							1.9435,
							1.4132,
							1.0697,
							1.4036
						],
						"confidence": 0.994,
						"span": {
							"offset": 0,
							"length": 6
						}
					},
					{
						"content": "Innovation",
						"polygon": [
							1.0697,
							1.5421,
							1.6904,
							1.5373,
							1.6904,
							1.6949,
							1.0697,
							1.6758
						],
						"confidence": 0.973,
						"span": {
							"offset": 7,
							"length": 10
						}
					},
					{
						"content": "drives",
						"polygon": [
							1.743,
							1.5373,
							2.1154,
							1.5373,
							2.1154,
							1.6997,
							1.743,
							1.6949
						],
						"confidence": 0.994,
						"span": {
							"offset": 18,
							"length": 6
						}
					},
					{
						"content": "progress",
						"polygon": [
							2.1441,
							1.5373,
							2.7028,
							1.5421,
							2.7028,
							1.6997,
							2.1441,
							1.6997
						],
						"confidence": 0.985,
						"span": {
							"offset": 25,
							"length": 8
						}
					},
					{
						"content": "PRODUCT",
						"polygon": [
							1.0267,
							3.2322,
							1.7478,
							3.237,
							1.7478,
							3.385,
							1.0315,
							3.385
						],
						"confidence": 0.994,
						"span": {
							"offset": 34,
							"length": 7
						}
					},
					{
						"content": "ID",
						"polygon": [
							1.786,
							3.237,
							1.9244,
							3.237,
							1.9244,
							3.385,
							1.786,
							3.385
						],
						"confidence": 0.996,
						"span": {
							"offset": 42,
							"length": 2
						}
					},
					{
						"content": "UNIT",
						"polygon": [
							2.4736,
							3.2322,
							2.8222,
							3.2322,
							2.8222,
							3.385,
							2.4736,
							3.385
						],
						"confidence": 0.989,
						"span": {
							"offset": 45,
							"length": 4
						}
					},
					{
						"content": "PRICE",
						"polygon": [
							2.8604,
							3.2322,
							3.2854,
							3.2322,
							3.2902,
							3.385,
							2.8604,
							3.385
						],
						"confidence": 0.995,
						"span": {
							"offset": 50,
							"length": 5
						}
					},
					{
						"content": "QUANTITY",
						"polygon": [
							3.4048,
							3.2322,
							4.164,
							3.2322,
							4.164,
							3.385,
							3.4096,
							3.385
						],
						"confidence": 0.995,
						"span": {
							"offset": 56,
							"length": 8
						}
					},
					{
						"content": "TOTAL",
						"polygon": [
							4.293,
							3.2322,
							4.761,
							3.2322,
							4.7562,
							3.385,
							4.293,
							3.385
						],
						"confidence": 0.995,
						"span": {
							"offset": 65,
							"length": 5
						}
					},
					{
						"content": "PRICE",
						"polygon": [
							4.8183,
							3.2322,
							5.248,
							3.2322,
							5.2433,
							3.385,
							4.8183,
							3.385
						],
						"confidence": 0.995,
						"span": {
							"offset": 71,
							"length": 5
						}
					},
					{
						"content": "INVOICE",
						"polygon": [
							6.0598,
							1.2222,
							7.3778,
							1.227,
							7.3826,
							1.5182,
							6.0598,
							1.5278
						],
						"confidence": 0.993,
						"span": {
							"offset": 77,
							"length": 7
						}
					},
					{
						"content": "Customer:",
						"polygon": [
							4.0733,
							1.8715,
							4.7753,
							1.8811,
							4.7753,
							2.01,
							4.0733,
							2.01
						],
						"confidence": 0.993,
						"span": {
							"offset": 85,
							"length": 9
						}
					},
					{
						"content": "Hessel",
						"polygon": [
							4.9138,
							1.8715,
							5.3435,
							1.8763,
							5.3435,
							2.01,
							4.9138,
							2.0052
						],
						"confidence": 0.995,
						"span": {
							"offset": 95,
							"length": 6
						}
					},
					{
						"content": "Address:",
						"polygon": [
							4.0733,
							2.0386,
							4.675,
							2.0482,
							4.675,
							2.1866,
							4.0781,
							2.1771
						],
						"confidence": 0.993,
						"span": {
							"offset": 102,
							"length": 8
						}
					},
					{
						"content": "41",
						"polygon": [
							4.909,
							2.0482,
							5.0666,
							2.0482,
							5.0666,
							2.1962,
							4.9138,
							2.1962
						],
						"confidence": 0.996,
						"span": {
							"offset": 111,
							"length": 2
						}
					},
					{
						"content": "Borough",
						"polygon": [
							5.0952,
							2.0482,
							5.6205,
							2.0482,
							5.6253,
							2.201,
							5.1,
							2.1962
						],
						"confidence": 0.995,
						"span": {
							"offset": 114,
							"length": 7
						}
					},
					{
						"content": "Road,",
						"polygon": [
							5.6635,
							2.0482,
							6.0312,
							2.0482,
							6.0312,
							2.201,
							5.6635,
							2.201
						],
						"confidence": 0.994,
						"span": {
							"offset": 122,
							"length": 5
						}
					},
					{
						"content": "Birmingham,",
						"polygon": [
							6.0598,
							2.0482,
							6.843,
							2.0434,
							6.843,
							2.1962,
							6.0598,
							2.201
						],
						"confidence": 0.993,
						"span": {
							"offset": 128,
							"length": 11
						}
					},
					{
						"content": "B1",
						"polygon": [
							6.8716,
							2.0434,
							7.0531,
							2.0434,
							7.0531,
							2.1914,
							6.8764,
							2.1962
						],
						"confidence": 0.995,
						"span": {
							"offset": 140,
							"length": 2
						}
					},
					{
						"content": "5NB",
						"polygon": [
							7.0817,
							2.0434,
							7.3396,
							2.0434,
							7.3396,
							2.1914,
							7.0817,
							2.1914
						],
						"confidence": 0.995,
						"span": {
							"offset": 143,
							"length": 3
						}
					},
					{
						"content": "Delivery",
						"polygon": [
							4.0733,
							2.2153,
							4.6177,
							2.2248,
							4.6177,
							2.3776,
							4.0733,
							2.3633
						],
						"confidence": 0.995,
						"span": {
							"offset": 147,
							"length": 8
						}
					},
					{
						"content": "Date:",
						"polygon": [
							4.0733,
							2.3776,
							4.4219,
							2.3776,
							4.4219,
							2.5065,
							4.0733,
							2.5017
						],
						"confidence": 0.995,
						"span": {
							"offset": 156,
							"length": 5
						}
					},
					{
						"content": "6/19/2024",
						"polygon": [
							4.9138,
							2.2201,
							5.5298,
							2.2201,
							5.5346,
							2.3633,
							4.9138,
							2.3537
						],
						"confidence": 0.995,
						"span": {
							"offset": 162,
							"length": 9
						}
					},
					{
						"content": "Invoice",
						"polygon": [
							4.0542,
							2.5399,
							4.5461,
							2.5399,
							4.5461,
							2.6832,
							4.059,
							2.6832
						],
						"confidence": 0.971,
						"span": {
							"offset": 172,
							"length": 7
						}
					},
					{
						"content": "#:",
						"polygon": [
							4.5843,
							2.5447,
							4.7228,
							2.5447,
							4.7275,
							2.6832,
							4.5843,
							2.6832
						],
						"confidence": 0.951,
						"span": {
							"offset": 180,
							"length": 2
						}
					},
					{
						"content": "4441423",
						"polygon": [
							4.9185,
							2.5495,
							5.4581,
							2.5495,
							5.4581,
							2.6879,
							4.9185,
							2.6832
						],
						"confidence": 0.995,
						"span": {
							"offset": 183,
							"length": 7
						}
					},
					{
						"content": "Purchase",
						"polygon": [
							5.6874,
							2.5447,
							6.3034,
							2.5495,
							6.3034,
							2.6975,
							5.6921,
							2.6927
						],
						"confidence": 0.994,
						"span": {
							"offset": 191,
							"length": 8
						}
					},
					{
						"content": "Order:",
						"polygon": [
							6.3416,
							2.5495,
							6.7809,
							2.5447,
							6.7809,
							2.6927,
							6.3416,
							2.6975
						],
						"confidence": 0.994,
						"span": {
							"offset": 200,
							"length": 6
						}
					},
					{
						"content": "17211",
						"polygon": [
							6.9719,
							2.5447,
							7.3444,
							2.5447,
							7.3444,
							2.6832,
							6.9719,
							2.6784
						],
						"confidence": 0.995,
						"span": {
							"offset": 207,
							"length": 5
						}
					},
					{
						"content": "JB508",
						"polygon": [
							1.1365,
							3.5569,
							1.552,
							3.5521,
							1.552,
							3.6905,
							1.1365,
							3.6905
						],
						"confidence": 0.995,
						"span": {
							"offset": 213,
							"length": 5
						}
					},
					{
						"content": "9.50",
						"polygon": [
							2.5691,
							3.5473,
							2.8652,
							3.5521,
							2.8652,
							3.6905,
							2.5691,
							3.6858
						],
						"confidence": 0.99,
						"span": {
							"offset": 219,
							"length": 4
						}
					},
					{
						"content": "2",
						"polygon": [
							3.5194,
							3.5616,
							3.5862,
							3.5616,
							3.5815,
							3.6858,
							3.5146,
							3.681
						],
						"confidence": 0.949,
						"span": {
							"offset": 224,
							"length": 1
						}
					},
					{
						"content": "19.00",
						"polygon": [
							7.077,
							3.5473,
							7.4494,
							3.5473,
							7.4494,
							3.6905,
							7.077,
							3.6905
						],
						"confidence": 0.995,
						"span": {
							"offset": 226,
							"length": 5
						}
					},
					{
						"content": "PL-14X",
						"polygon": [
							1.1317,
							3.8863,
							1.614,
							3.8863,
							1.614,
							4.0152,
							1.1317,
							4.02
						],
						"confidence": 0.961,
						"span": {
							"offset": 232,
							"length": 6
						}
					},
					{
						"content": "5.25",
						"polygon": [
							2.5643,
							3.8624,
							2.8747,
							3.8624,
							2.8699,
							4.0295,
							2.5643,
							4.0247
						],
						"confidence": 0.993,
						"span": {
							"offset": 239,
							"length": 4
						}
					},
					{
						"content": "1",
						"polygon": [
							3.5242,
							3.8815,
							3.5719,
							3.8815,
							3.5719,
							4.0056,
							3.5242,
							4.0056
						],
						"confidence": 0.995,
						"span": {
							"offset": 244,
							"length": 1
						}
					},
					{
						"content": "5.25",
						"polygon": [
							7.1486,
							3.8815,
							7.4447,
							3.8815,
							7.4447,
							4.02,
							7.1486,
							4.0152
						],
						"confidence": 0.993,
						"span": {
							"offset": 246,
							"length": 4
						}
					},
					{
						"content": "TOTAL",
						"polygon": [
							1.1461,
							4.2062,
							1.6093,
							4.2062,
							1.6093,
							4.3398,
							1.1461,
							4.3446
						],
						"confidence": 0.995,
						"span": {
							"offset": 251,
							"length": 5
						}
					},
					{
						"content": "3",
						"polygon": [
							3.5194,
							4.2109,
							3.5815,
							4.2109,
							3.5862,
							4.3255,
							3.5242,
							4.3255
						],
						"confidence": 0.997,
						"span": {
							"offset": 257,
							"length": 1
						}
					},
					{
						"content": "24.25",
						"polygon": [
							7.077,
							4.2109,
							7.4399,
							4.2062,
							7.4399,
							4.3494,
							7.0817,
							4.3446
						],
						"confidence": 0.995,
						"span": {
							"offset": 259,
							"length": 5
						}
					},
					{
						"content": "CUSTOMER",
						"polygon": [
							1.1365,
							4.6836,
							1.9435,
							4.6788,
							1.9483,
							4.822,
							1.1365,
							4.8268
						],
						"confidence": 0.994,
						"span": {
							"offset": 265,
							"length": 8
						}
					},
					{
						"content": "SIGNATURE:",
						"polygon": [
							2.0199,
							4.6788,
							2.9081,
							4.6836,
							2.9081,
							4.822,
							2.0199,
							4.822
						],
						"confidence": 0.983,
						"span": {
							"offset": 274,
							"length": 10
						}
					},
					{
						"content": "NAME:",
						"polygon": [
							5.1334,
							4.6931,
							5.6301,
							4.6931,
							5.6348,
							4.8411,
							5.1334,
							4.8364
						],
						"confidence": 0.994,
						"span": {
							"offset": 285,
							"length": 5
						}
					},
					{
						"content": "Sarah",
						"polygon": [
							5.6587,
							4.6931,
							6.0312,
							4.6931,
							6.0312,
							4.8364,
							5.6635,
							4.8411
						],
						"confidence": 0.995,
						"span": {
							"offset": 291,
							"length": 5
						}
					},
					{
						"content": "P",
						"polygon": [
							6.0837,
							4.6931,
							6.1601,
							4.6931,
							6.1649,
							4.8364,
							6.0885,
							4.8364
						],
						"confidence": 0.996,
						"span": {
							"offset": 297,
							"length": 1
						}
					},
					{
						"content": "DRIVER",
						"polygon": [
							1.1365,
							5.0035,
							1.6475,
							5.0035,
							1.6475,
							5.1515,
							1.1413,
							5.1515
						],
						"confidence": 0.994,
						"span": {
							"offset": 299,
							"length": 6
						}
					},
					{
						"content": "SIGNATURE:",
						"polygon": [
							1.7239,
							5.0035,
							2.6169,
							5.0082,
							2.6169,
							5.1419,
							1.7239,
							5.1515
						],
						"confidence": 0.986,
						"span": {
							"offset": 306,
							"length": 10
						}
					},
					{
						"content": "NAME:",
						"polygon": [
							5.1334,
							5.013,
							5.6301,
							5.0226,
							5.6301,
							5.161,
							5.1334,
							5.1658
						],
						"confidence": 0.993,
						"span": {
							"offset": 317,
							"length": 5
						}
					},
					{
						"content": "James",
						"polygon": [
							5.6587,
							5.0226,
							6.0789,
							5.0178,
							6.0789,
							5.161,
							5.6587,
							5.161
						],
						"confidence": 0.993,
						"span": {
							"offset": 323,
							"length": 5
						}
					},
					{
						"content": "T",
						"polygon": [
							6.1362,
							5.0178,
							6.2126,
							5.013,
							6.2126,
							5.161,
							6.1362,
							5.161
						],
						"confidence": 0.995,
						"span": {
							"offset": 329,
							"length": 1
						}
					}
				],
				"lines": [
					{
						"content": "NEXGEN",
						"polygon": [
							1.0649,
							1.2031,
							2.0104,
							1.2031,
							2.0104,
							1.4084,
							1.0649,
							1.4036
						],
						"spans": [
							{
								"offset": 0,
								"length": 6
							}
						]
					},
					{
						"content": "Innovation drives progress",
						"polygon": [
							1.0649,
							1.5326,
							2.7028,
							1.5373,
							2.7028,
							1.6949,
							1.0649,
							1.6853
						],
						"spans": [
							{
								"offset": 7,
								"length": 26
							}
						]
					},
					{
						"content": "PRODUCT ID",
						"polygon": [
							1.0267,
							3.2322,
							1.9531,
							3.2322,
							1.9531,
							3.3802,
							1.0267,
							3.3802
						],
						"spans": [
							{
								"offset": 34,
								"length": 10
							}
						]
					},
					{
						"content": "UNIT PRICE QUANTITY TOTAL PRICE",
						"polygon": [
							2.464,
							3.2322,
							5.2719,
							3.2274,
							5.2719,
							3.3802,
							2.464,
							3.3802
						],
						"spans": [
							{
								"offset": 45,
								"length": 31
							}
						]
					},
					{
						"content": "INVOICE",
						"polygon": [
							6.0598,
							1.2222,
							7.416,
							1.2222,
							7.416,
							1.5182,
							6.0598,
							1.523
						],
						"spans": [
							{
								"offset": 77,
								"length": 7
							}
						]
					},
					{
						"content": "Customer:",
						"polygon": [
							4.0542,
							1.8668,
							4.7705,
							1.8763,
							4.7705,
							2.01,
							4.0542,
							2.0052
						],
						"spans": [
							{
								"offset": 85,
								"length": 9
							}
						]
					},
					{
						"content": "Hessel",
						"polygon": [
							4.909,
							1.8715,
							5.3483,
							1.8763,
							5.3435,
							2.01,
							4.909,
							2.0004
						],
						"spans": [
							{
								"offset": 95,
								"length": 6
							}
						]
					},
					{
						"content": "Address:",
						"polygon": [
							4.0542,
							2.0386,
							4.675,
							2.0434,
							4.675,
							2.1819,
							4.0542,
							2.1723
						],
						"spans": [
							{
								"offset": 102,
								"length": 8
							}
						]
					},
					{
						"content": "41 Borough Road, Birmingham, B1 5NB",
						"polygon": [
							4.909,
							2.0434,
							7.3635,
							2.0434,
							7.3635,
							2.1914,
							4.909,
							2.1962
						],
						"spans": [
							{
								"offset": 111,
								"length": 35
							}
						]
					},
					{
						"content": "Delivery",
						"polygon": [
							4.0638,
							2.2105,
							4.6177,
							2.2248,
							4.6177,
							2.3728,
							4.0638,
							2.3585
						],
						"spans": [
							{
								"offset": 147,
								"length": 8
							}
						]
					},
					{
						"content": "Date:",
						"polygon": [
							4.0685,
							2.3776,
							4.4219,
							2.3776,
							4.4219,
							2.5065,
							4.0685,
							2.5017
						],
						"spans": [
							{
								"offset": 156,
								"length": 5
							}
						]
					},
					{
						"content": "6/19/2024",
						"polygon": [
							4.909,
							2.2153,
							5.5441,
							2.2153,
							5.5441,
							2.3585,
							4.909,
							2.349
						],
						"spans": [
							{
								"offset": 162,
								"length": 9
							}
						]
					},
					{
						"content": "Invoice #:",
						"polygon": [
							4.0542,
							2.5352,
							4.7228,
							2.5399,
							4.7228,
							2.6832,
							4.0542,
							2.6784
						],
						"spans": [
							{
								"offset": 172,
								"length": 10
							}
						]
					},
					{
						"content": "4441423",
						"polygon": [
							4.909,
							2.5447,
							5.4725,
							2.5447,
							5.4677,
							2.6879,
							4.909,
							2.6784
						],
						"spans": [
							{
								"offset": 183,
								"length": 7
							}
						]
					},
					{
						"content": "Purchase Order:",
						"polygon": [
							5.6874,
							2.5447,
							6.7857,
							2.5447,
							6.7857,
							2.6927,
							5.6874,
							2.6879
						],
						"spans": [
							{
								"offset": 191,
								"length": 15
							}
						]
					},
					{
						"content": "17211",
						"polygon": [
							6.9576,
							2.5447,
							7.3492,
							2.5447,
							7.3444,
							2.6832,
							6.9624,
							2.6784
						],
						"spans": [
							{
								"offset": 207,
								"length": 5
							}
						]
					},
					{
						"content": "JB508",
						"polygon": [
							1.127,
							3.5521,
							1.552,
							3.5521,
							1.552,
							3.6858,
							1.127,
							3.6858
						],
						"spans": [
							{
								"offset": 213,
								"length": 5
							}
						]
					},
					{
						"content": "9.50",
						"polygon": [
							2.5548,
							3.5473,
							2.8699,
							3.5521,
							2.8652,
							3.6905,
							2.5596,
							3.6858
						],
						"spans": [
							{
								"offset": 219,
								"length": 4
							}
						]
					},
					{
						"content": "2",
						"polygon": [
							3.5051,
							3.5616,
							3.5958,
							3.5616,
							3.591,
							3.6858,
							3.5051,
							3.6762
						],
						"spans": [
							{
								"offset": 224,
								"length": 1
							}
						]
					},
					{
						"content": "19.00",
						"polygon": [
							7.0722,
							3.5473,
							7.459,
							3.5473,
							7.4638,
							3.6905,
							7.077,
							3.6905
						],
						"spans": [
							{
								"offset": 226,
								"length": 5
							}
						]
					},
					{
						"content": "PL-14X",
						"polygon": [
							1.127,
							3.8815,
							1.614,
							3.8815,
							1.614,
							4.0104,
							1.1317,
							4.0152
						],
						"spans": [
							{
								"offset": 232,
								"length": 6
							}
						]
					},
					{
						"content": "5.25",
						"polygon": [
							2.5643,
							3.8624,
							2.8843,
							3.8624,
							2.8843,
							4.0295,
							2.5643,
							4.0247
						],
						"spans": [
							{
								"offset": 239,
								"length": 4
							}
						]
					},
					{
						"content": "1",
						"polygon": [
							3.5242,
							3.8863,
							3.5815,
							3.8815,
							3.5862,
							4.0056,
							3.5289,
							4.0009
						],
						"spans": [
							{
								"offset": 244,
								"length": 1
							}
						]
					},
					{
						"content": "5.25",
						"polygon": [
							7.1438,
							3.8815,
							7.459,
							3.8815,
							7.459,
							4.02,
							7.1438,
							4.0152
						],
						"spans": [
							{
								"offset": 246,
								"length": 4
							}
						]
					},
					{
						"content": "TOTAL",
						"polygon": [
							1.127,
							4.2014,
							1.614,
							4.2014,
							1.614,
							4.3398,
							1.127,
							4.3398
						],
						"spans": [
							{
								"offset": 251,
								"length": 5
							}
						]
					},
					{
						"content": "3",
						"polygon": [
							3.5098,
							4.2157,
							3.591,
							4.2109,
							3.591,
							4.3255,
							3.5098,
							4.3255
						],
						"spans": [
							{
								"offset": 257,
								"length": 1
							}
						]
					},
					{
						"content": "24.25",
						"polygon": [
							7.0579,
							4.2062,
							7.459,
							4.2062,
							7.459,
							4.3446,
							7.0579,
							4.3398
						],
						"spans": [
							{
								"offset": 259,
								"length": 5
							}
						]
					},
					{
						"content": "CUSTOMER SIGNATURE:",
						"polygon": [
							1.127,
							4.674,
							2.9081,
							4.674,
							2.9081,
							4.822,
							1.127,
							4.822
						],
						"spans": [
							{
								"offset": 265,
								"length": 19
							}
						]
					},
					{
						"content": "NAME: Sarah P",
						"polygon": [
							5.1287,
							4.6884,
							6.184,
							4.6884,
							6.184,
							4.8316,
							5.1287,
							4.8364
						],
						"spans": [
							{
								"offset": 285,
								"length": 13
							}
						]
					},
					{
						"content": "DRIVER SIGNATURE:",
						"polygon": [
							1.1365,
							4.9987,
							2.6216,
							4.9987,
							2.6216,
							5.1467,
							1.1365,
							5.1467
						],
						"spans": [
							{
								"offset": 299,
								"length": 17
							}
						]
					},
					{
						"content": "NAME: James T",
						"polygon": [
							5.1287,
							5.013,
							6.2222,
							5.013,
							6.2222,
							5.161,
							5.1287,
							5.161
						],
						"spans": [
							{
								"offset": 317,
								"length": 13
							}
						]
					}
				],
				"spans": [
					{
						"offset": 0,
						"length": 330
					}
				]
			},
			{
				"pageNumber": 2,
				"angle": 0.20609639585018158,
				"width": 8.5,
				"height": 11,
				"unit": "inch",
				"words": [
					{
						"content": "NEXGEN",
						"polygon": [
							1.0697,
							1.2127,
							1.9435,
							1.2079,
							1.9435,
							1.4132,
							1.0697,
							1.4036
						],
						"confidence": 0.994,
						"span": {
							"offset": 331,
							"length": 6
						}
					},
					{
						"content": "Innovation",
						"polygon": [
							1.0697,
							1.5421,
							1.6904,
							1.5373,
							1.6904,
							1.6949,
							1.0697,
							1.6758
						],
						"confidence": 0.973,
						"span": {
							"offset": 338,
							"length": 10
						}
					},
					{
						"content": "drives",
						"polygon": [
							1.743,
							1.5373,
							2.1154,
							1.5373,
							2.1154,
							1.6997,
							1.743,
							1.6949
						],
						"confidence": 0.994,
						"span": {
							"offset": 349,
							"length": 6
						}
					},
					{
						"content": "progress",
						"polygon": [
							2.1441,
							1.5373,
							2.7028,
							1.5421,
							2.7028,
							1.6997,
							2.1441,
							1.6997
						],
						"confidence": 0.985,
						"span": {
							"offset": 356,
							"length": 8
						}
					},
					{
						"content": "RETURNS",
						"polygon": [
							5.8784,
							1.2318,
							7.3683,
							1.227,
							7.3683,
							1.5182,
							5.8784,
							1.523
						],
						"confidence": 0.994,
						"span": {
							"offset": 365,
							"length": 7
						}
					},
					{
						"content": "Customer:",
						"polygon": [
							4.0733,
							1.8715,
							4.7753,
							1.8811,
							4.7753,
							2.01,
							4.0733,
							2.01
						],
						"confidence": 0.993,
						"span": {
							"offset": 373,
							"length": 9
						}
					},
					{
						"content": "Hessel",
						"polygon": [
							4.9138,
							1.8715,
							5.3483,
							1.8811,
							5.3483,
							2.0148,
							4.9138,
							2.0052
						],
						"confidence": 0.995,
						"span": {
							"offset": 383,
							"length": 6
						}
					},
					{
						"content": "Address:",
						"polygon": [
							4.0733,
							2.0386,
							4.675,
							2.0482,
							4.675,
							2.1866,
							4.0781,
							2.1771
						],
						"confidence": 0.993,
						"span": {
							"offset": 390,
							"length": 8
						}
					},
					{
						"content": "41",
						"polygon": [
							4.909,
							2.0482,
							5.0666,
							2.0482,
							5.0666,
							2.1962,
							4.9138,
							2.1962
						],
						"confidence": 0.996,
						"span": {
							"offset": 399,
							"length": 2
						}
					},
					{
						"content": "Borough",
						"polygon": [
							5.0952,
							2.0482,
							5.6205,
							2.0482,
							5.6205,
							2.201,
							5.1,
							2.1962
						],
						"confidence": 0.995,
						"span": {
							"offset": 402,
							"length": 7
						}
					},
					{
						"content": "Road,",
						"polygon": [
							5.6587,
							2.0482,
							6.0264,
							2.0482,
							6.0264,
							2.201,
							5.6635,
							2.201
						],
						"confidence": 0.995,
						"span": {
							"offset": 410,
							"length": 5
						}
					},
					{
						"content": "Birmingham,",
						"polygon": [
							6.0551,
							2.0482,
							6.8478,
							2.0434,
							6.8525,
							2.1962,
							6.0598,
							2.201
						],
						"confidence": 0.993,
						"span": {
							"offset": 416,
							"length": 11
						}
					},
					{
						"content": "B1",
						"polygon": [
							6.8812,
							2.0434,
							7.0579,
							2.0434,
							7.0579,
							2.1914,
							6.8812,
							2.1962
						],
						"confidence": 0.995,
						"span": {
							"offset": 428,
							"length": 2
						}
					},
					{
						"content": "5NB",
						"polygon": [
							7.0865,
							2.0434,
							7.3348,
							2.0434,
							7.3348,
							2.1914,
							7.0865,
							2.1914
						],
						"confidence": 0.997,
						"span": {
							"offset": 431,
							"length": 3
						}
					},
					{
						"content": "Delivery",
						"polygon": [
							4.0733,
							2.2153,
							4.6129,
							2.2248,
							4.6129,
							2.3776,
							4.0733,
							2.3585
						],
						"confidence": 0.995,
						"span": {
							"offset": 435,
							"length": 8
						}
					},
					{
						"content": "Date:",
						"polygon": [
							4.0733,
							2.3776,
							4.4219,
							2.3776,
							4.4219,
							2.5065,
							4.0733,
							2.5017
						],
						"confidence": 0.995,
						"span": {
							"offset": 444,
							"length": 5
						}
					},
					{
						"content": "6/19/2024",
						"polygon": [
							4.909,
							2.2105,
							5.5393,
							2.2105,
							5.5393,
							2.3776,
							4.9042,
							2.3633
						],
						"confidence": 0.994,
						"span": {
							"offset": 450,
							"length": 9
						}
					},
					{
						"content": "Invoice",
						"polygon": [
							4.059,
							2.5399,
							4.5413,
							2.5447,
							4.5413,
							2.6832,
							4.059,
							2.6784
						],
						"confidence": 0.961,
						"span": {
							"offset": 460,
							"length": 7
						}
					},
					{
						"content": "#:",
						"polygon": [
							4.5747,
							2.5447,
							4.7132,
							2.5447,
							4.718,
							2.6832,
							4.5795,
							2.6832
						],
						"confidence": 0.963,
						"span": {
							"offset": 468,
							"length": 2
						}
					},
					{
						"content": "4441423",
						"polygon": [
							4.9138,
							2.5495,
							5.4581,
							2.5495,
							5.4581,
							2.6927,
							4.9138,
							2.6832
						],
						"confidence": 0.995,
						"span": {
							"offset": 471,
							"length": 7
						}
					},
					{
						"content": "Purchase",
						"polygon": [
							5.6874,
							2.5447,
							6.3034,
							2.5495,
							6.3081,
							2.6975,
							5.6921,
							2.6927
						],
						"confidence": 0.994,
						"span": {
							"offset": 479,
							"length": 8
						}
					},
					{
						"content": "Order:",
						"polygon": [
							6.3463,
							2.5495,
							6.7809,
							2.5447,
							6.7857,
							2.6927,
							6.3463,
							2.6975
						],
						"confidence": 0.994,
						"span": {
							"offset": 488,
							"length": 6
						}
					},
					{
						"content": "17211",
						"polygon": [
							6.9719,
							2.5399,
							7.3348,
							2.5447,
							7.3348,
							2.6832,
							6.9719,
							2.6784
						],
						"confidence": 0.995,
						"span": {
							"offset": 495,
							"length": 5
						}
					},
					{
						"content": "PRODUCT",
						"polygon": [
							1.0267,
							3.2322,
							1.7621,
							3.237,
							1.7621,
							3.385,
							1.0315,
							3.3898
						],
						"confidence": 0.994,
						"span": {
							"offset": 501,
							"length": 7
						}
					},
					{
						"content": "ID",
						"polygon": [
							1.7907,
							3.237,
							1.9292,
							3.237,
							1.9292,
							3.385,
							1.7907,
							3.385
						],
						"confidence": 0.996,
						"span": {
							"offset": 509,
							"length": 2
						}
					},
					{
						"content": "QUANTITY",
						"polygon": [
							2.4736,
							3.2274,
							3.2281,
							3.2274,
							3.2281,
							3.3898,
							2.4688,
							3.3945
						],
						"confidence": 0.994,
						"span": {
							"offset": 512,
							"length": 8
						}
					},
					{
						"content": "REASON",
						"polygon": [
							3.3475,
							3.2274,
							3.9348,
							3.2274,
							3.9301,
							3.3898,
							3.3427,
							3.3898
						],
						"confidence": 0.995,
						"span": {
							"offset": 521,
							"length": 6
						}
					},
					{
						"content": "TOTAL",
						"polygon": [
							1.1461,
							3.8815,
							1.614,
							3.8815,
							1.614,
							4.0152,
							1.1461,
							4.02
						],
						"confidence": 0.995,
						"span": {
							"offset": 528,
							"length": 5
						}
					},
					{
						"content": "0",
						"polygon": [
							2.5739,
							3.8863,
							2.636,
							3.8863,
							2.636,
							4.0009,
							2.5739,
							4.0009
						],
						"confidence": 0.991,
						"span": {
							"offset": 534,
							"length": 1
						}
					},
					{
						"content": "CUSTOMER",
						"polygon": [
							1.1365,
							4.3685,
							1.9435,
							4.3637,
							1.9435,
							4.5117,
							1.1365,
							4.5165
						],
						"confidence": 0.994,
						"span": {
							"offset": 536,
							"length": 8
						}
					},
					{
						"content": "SIGNATURE:",
						"polygon": [
							2.0199,
							4.3637,
							2.9081,
							4.3637,
							2.9081,
							4.5165,
							2.0199,
							4.5117
						],
						"confidence": 0.988,
						"span": {
							"offset": 545,
							"length": 10
						}
					},
					{
						"content": "NAME:",
						"polygon": [
							5.1334,
							4.3733,
							5.611,
							4.3733,
							5.611,
							4.5165,
							5.1334,
							4.5069
						],
						"confidence": 0.993,
						"span": {
							"offset": 556,
							"length": 5
						}
					},
					{
						"content": "DRIVER",
						"polygon": [
							1.1317,
							4.6836,
							1.6522,
							4.6788,
							1.657,
							4.822,
							1.1317,
							4.822
						],
						"confidence": 0.995,
						"span": {
							"offset": 562,
							"length": 6
						}
					},
					{
						"content": "SIGNATURE:",
						"polygon": [
							1.7287,
							4.6788,
							2.6216,
							4.6836,
							2.6216,
							4.8268,
							1.7287,
							4.822
						],
						"confidence": 0.988,
						"span": {
							"offset": 569,
							"length": 10
						}
					},
					{
						"content": "NAME:",
						"polygon": [
							5.1239,
							4.6836,
							5.6205,
							4.6884,
							5.6157,
							4.8507,
							5.1191,
							4.8555
						],
						"confidence": 0.994,
						"span": {
							"offset": 580,
							"length": 5
						}
					},
					{
						"content": "James",
						"polygon": [
							5.6492,
							4.6884,
							6.0933,
							4.6836,
							6.0933,
							4.8459,
							5.6492,
							4.8507
						],
						"confidence": 0.984,
						"span": {
							"offset": 586,
							"length": 5
						}
					},
					{
						"content": "T",
						"polygon": [
							6.1362,
							4.6836,
							6.2174,
							4.6836,
							6.2174,
							4.8459,
							6.1362,
							4.8459
						],
						"confidence": 0.992,
						"span": {
							"offset": 592,
							"length": 1
						}
					}
				],
				"lines": [
					{
						"content": "NEXGEN",
						"polygon": [
							1.0649,
							1.2031,
							2.0104,
							1.2031,
							2.0104,
							1.4084,
							1.0649,
							1.4036
						],
						"spans": [
							{
								"offset": 331,
								"length": 6
							}
						]
					},
					{
						"content": "Innovation drives progress",
						"polygon": [
							1.0649,
							1.5326,
							2.7028,
							1.5373,
							2.7028,
							1.6949,
							1.0649,
							1.6853
						],
						"spans": [
							{
								"offset": 338,
								"length": 26
							}
						]
					},
					{
						"content": "RETURNS",
						"polygon": [
							5.8784,
							1.2318,
							7.4017,
							1.2222,
							7.4065,
							1.5135,
							5.8784,
							1.523
						],
						"spans": [
							{
								"offset": 365,
								"length": 7
							}
						]
					},
					{
						"content": "Customer:",
						"polygon": [
							4.0542,
							1.8668,
							4.7705,
							1.8763,
							4.7705,
							2.01,
							4.0542,
							2.0052
						],
						"spans": [
							{
								"offset": 373,
								"length": 9
							}
						]
					},
					{
						"content": "Hessel",
						"polygon": [
							4.909,
							1.8715,
							5.3483,
							1.8763,
							5.3435,
							2.01,
							4.909,
							2.0004
						],
						"spans": [
							{
								"offset": 383,
								"length": 6
							}
						]
					},
					{
						"content": "Address:",
						"polygon": [
							4.0542,
							2.0386,
							4.675,
							2.0434,
							4.675,
							2.1819,
							4.0542,
							2.1723
						],
						"spans": [
							{
								"offset": 390,
								"length": 8
							}
						]
					},
					{
						"content": "41 Borough Road, Birmingham, B1 5NB",
						"polygon": [
							4.909,
							2.0434,
							7.3635,
							2.0386,
							7.3635,
							2.1914,
							4.909,
							2.1962
						],
						"spans": [
							{
								"offset": 399,
								"length": 35
							}
						]
					},
					{
						"content": "Delivery",
						"polygon": [
							4.0638,
							2.2153,
							4.6177,
							2.2248,
							4.6177,
							2.3728,
							4.0638,
							2.3585
						],
						"spans": [
							{
								"offset": 435,
								"length": 8
							}
						]
					},
					{
						"content": "Date:",
						"polygon": [
							4.0685,
							2.3776,
							4.4219,
							2.3776,
							4.4219,
							2.5065,
							4.0733,
							2.5017
						],
						"spans": [
							{
								"offset": 444,
								"length": 5
							}
						]
					},
					{
						"content": "6/19/2024",
						"polygon": [
							4.9042,
							2.2057,
							5.5489,
							2.2057,
							5.5489,
							2.3728,
							4.9042,
							2.3681
						],
						"spans": [
							{
								"offset": 450,
								"length": 9
							}
						]
					},
					{
						"content": "Invoice #:",
						"polygon": [
							4.0542,
							2.5352,
							4.718,
							2.5399,
							4.718,
							2.6784,
							4.0542,
							2.6784
						],
						"spans": [
							{
								"offset": 460,
								"length": 10
							}
						]
					},
					{
						"content": "4441423",
						"polygon": [
							4.909,
							2.5447,
							5.4677,
							2.5447,
							5.4677,
							2.6879,
							4.909,
							2.6832
						],
						"spans": [
							{
								"offset": 471,
								"length": 7
							}
						]
					},
					{
						"content": "Purchase Order:",
						"polygon": [
							5.6874,
							2.5447,
							6.7857,
							2.5447,
							6.7857,
							2.6927,
							5.6874,
							2.6927
						],
						"spans": [
							{
								"offset": 479,
								"length": 15
							}
						]
					},
					{
						"content": "17211",
						"polygon": [
							6.9576,
							2.5399,
							7.3444,
							2.5447,
							7.3444,
							2.6832,
							6.9624,
							2.6784
						],
						"spans": [
							{
								"offset": 495,
								"length": 5
							}
						]
					},
					{
						"content": "PRODUCT ID",
						"polygon": [
							1.0267,
							3.2274,
							1.9483,
							3.2322,
							1.9483,
							3.385,
							1.0267,
							3.385
						],
						"spans": [
							{
								"offset": 501,
								"length": 10
							}
						]
					},
					{
						"content": "QUANTITY REASON",
						"polygon": [
							2.4593,
							3.2274,
							3.973,
							3.2274,
							3.973,
							3.385,
							2.4593,
							3.3898
						],
						"spans": [
							{
								"offset": 512,
								"length": 15
							}
						]
					},
					{
						"content": "TOTAL",
						"polygon": [
							1.127,
							3.8767,
							1.6236,
							3.8767,
							1.6236,
							4.0152,
							1.127,
							4.0152
						],
						"spans": [
							{
								"offset": 528,
								"length": 5
							}
						]
					},
					{
						"content": "0",
						"polygon": [
							2.5691,
							3.8863,
							2.6551,
							3.8863,
							2.6598,
							4.0009,
							2.5739,
							4.0009
						],
						"spans": [
							{
								"offset": 534,
								"length": 1
							}
						]
					},
					{
						"content": "CUSTOMER SIGNATURE:",
						"polygon": [
							1.127,
							4.3637,
							2.9129,
							4.3637,
							2.9129,
							4.5117,
							1.127,
							4.5165
						],
						"spans": [
							{
								"offset": 536,
								"length": 19
							}
						]
					},
					{
						"content": "NAME:",
						"polygon": [
							5.1287,
							4.3685,
							5.611,
							4.3733,
							5.6062,
							4.5117,
							5.1287,
							4.5022
						],
						"spans": [
							{
								"offset": 556,
								"length": 5
							}
						]
					},
					{
						"content": "DRIVER SIGNATURE:",
						"polygon": [
							1.127,
							4.6788,
							2.6169,
							4.6788,
							2.6169,
							4.822,
							1.127,
							4.822
						],
						"spans": [
							{
								"offset": 562,
								"length": 17
							}
						]
					},
					{
						"content": "NAME: James T",
						"polygon": [
							5.1191,
							4.6836,
							6.2126,
							4.6836,
							6.2126,
							4.8459,
							5.1191,
							4.8507
						],
						"spans": [
							{
								"offset": 580,
								"length": 13
							}
						]
					}
				],
				"spans": [
					{
						"offset": 331,
						"length": 262
					}
				]
			}
		],
		"tables": [
			{
				"rowCount": 4,
				"columnCount": 3,
				"cells": [
					{
						"rowIndex": 0,
						"columnIndex": 0,
						"content": "Customer:",
						"boundingRegions": [
							{
								"pageNumber": 1,
								"polygon": [
									4.0065,
									1.8524,
									4.8421,
									1.8524,
									4.8421,
									2.0195,
									4.0065,
									2.0195
								]
							}
						],
						"spans": [
							{
								"offset": 85,
								"length": 9
							}
						]
					},
					{
						"rowIndex": 0,
						"columnIndex": 1,
						"columnSpan": 2,
						"content": "Hessel",
						"boundingRegions": [
							{
								"pageNumber": 1,
								"polygon": [
									4.8421,
									1.8524,
									7.4924,
									1.8524,
									7.4924,
									2.0195,
									4.8421,
									2.0195
								]
							}
						],
						"spans": [
							{
								"offset": 95,
								"length": 6
							}
						]
					},
					{
						"rowIndex": 1,
						"columnIndex": 0,
						"content": "Address:",
						"boundingRegions": [
							{
								"pageNumber": 1,
								"polygon": [
									4.0065,
									2.0195,
									4.8421,
									2.0195,
									4.8421,
									2.1962,
									4.0065,
									2.1962
								]
							}
						],
						"spans": [
							{
								"offset": 102,
								"length": 8
							}
						]
					},
					{
						"rowIndex": 1,
						"columnIndex": 1,
						"columnSpan": 2,
						"content": "41 Borough Road, Birmingham, B1 5NB",
						"boundingRegions": [
							{
								"pageNumber": 1,
								"polygon": [
									4.8421,
									2.0195,
									7.4924,
									2.0195,
									7.4924,
									2.1962,
									4.8421,
									2.1962
								]
							}
						],
						"spans": [
							{
								"offset": 111,
								"length": 35
							}
						]
					},
					{
						"rowIndex": 2,
						"columnIndex": 0,
						"content": "Delivery Date:",
						"boundingRegions": [
							{
								"pageNumber": 1,
								"polygon": [
									4.0065,
									2.1962,
									4.8421,
									2.1962,
									4.8421,
									2.5208,
									4.0017,
									2.5208
								]
							}
						],
						"spans": [
							{
								"offset": 147,
								"length": 14
							}
						]
					},
					{
						"rowIndex": 2,
						"columnIndex": 1,
						"columnSpan": 2,
						"content": "6/19/2024",
						"boundingRegions": [
							{
								"pageNumber": 1,
								"polygon": [
									4.8421,
									2.1962,
									7.4924,
									2.1962,
									7.4924,
									2.5208,
									4.8421,
									2.5208
								]
							}
						],
						"spans": [
							{
								"offset": 162,
								"length": 9
							}
						]
					},
					{
						"rowIndex": 3,
						"columnIndex": 0,
						"content": "Invoice #:",
						"boundingRegions": [
							{
								"pageNumber": 1,
								"polygon": [
									4.0017,
									2.5208,
									4.8421,
									2.5208,
									4.8421,
									2.6975,
									4.0017,
									2.6975
								]
							}
						],
						"spans": [
							{
								"offset": 172,
								"length": 10
							}
						]
					},
					{
						"rowIndex": 3,
						"columnIndex": 1,
						"content": "4441423",
						"boundingRegions": [
							{
								"pageNumber": 1,
								"polygon": [
									4.8421,
									2.5208,
									5.6014,
									2.5208,
									5.6062,
									2.6975,
									4.8421,
									2.6975
								]
							}
						],
						"spans": [
							{
								"offset": 183,
								"length": 7
							}
						]
					},
					{
						"rowIndex": 3,
						"columnIndex": 2,
						"content": "Purchase Order: 17211",
						"boundingRegions": [
							{
								"pageNumber": 1,
								"polygon": [
									5.6014,
									2.5208,
									7.4924,
									2.5208,
									7.4972,
									2.6975,
									5.6062,
									2.6975
								]
							}
						],
						"spans": [
							{
								"offset": 191,
								"length": 21
							}
						]
					}
				],
				"boundingRegions": [
					{
						"pageNumber": 1,
						"polygon": [
							3.9995,
							1.8501,
							7.5045,
							1.8506,
							7.5039,
							2.7029,
							3.9985,
							2.7029
						]
					}
				],
				"spans": [
					{
						"offset": 85,
						"length": 127
					}
				]
			},
			{
				"rowCount": 3,
				"columnCount": 4,
				"cells": [
					{
						"rowIndex": 0,
						"columnIndex": 0,
						"content": "JB508",
						"boundingRegions": [
							{
								"pageNumber": 1,
								"polygon": [
									0.9984,
									3.4517,
									2.4315,
									3.4517,
									2.4315,
									3.7737,
									0.9917,
									3.7737
								]
							}
						],
						"spans": [
							{
								"offset": 213,
								"length": 5
							}
						]
					},
					{
						"rowIndex": 0,
						"columnIndex": 1,
						"content": "9.50",
						"boundingRegions": [
							{
								"pageNumber": 1,
								"polygon": [
									2.4315,
									3.4517,
									3.3757,
									3.4517,
									3.369,
									3.7737,
									2.4315,
									3.7737
								]
							}
						],
						"spans": [
							{
								"offset": 219,
								"length": 4
							}
						]
					},
					{
						"rowIndex": 0,
						"columnIndex": 2,
						"content": "2",
						"boundingRegions": [
							{
								"pageNumber": 1,
								"polygon": [
									3.3757,
									3.4517,
									4.2329,
									3.4517,
									4.2396,
									3.7737,
									3.369,
									3.7737
								]
							}
						],
						"spans": [
							{
								"offset": 224,
								"length": 1
							}
						]
					},
					{
						"rowIndex": 0,
						"columnIndex": 3,
						"content": "19.00",
						"boundingRegions": [
							{
								"pageNumber": 1,
								"polygon": [
									4.2329,
									3.4517,
									7.4941,
									3.4517,
									7.4941,
									3.767,
									4.2396,
									3.7737
								]
							}
						],
						"spans": [
							{
								"offset": 226,
								"length": 5
							}
						]
					},
					{
						"rowIndex": 1,
						"columnIndex": 0,
						"content": "PL-14X",
						"boundingRegions": [
							{
								"pageNumber": 1,
								"polygon": [
									0.9917,
									3.7737,
									2.4315,
									3.7737,
									2.4315,
									4.1091,
									0.9917,
									4.1091
								]
							}
						],
						"spans": [
							{
								"offset": 232,
								"length": 6
							}
						]
					},
					{
						"rowIndex": 1,
						"columnIndex": 1,
						"content": "5.25",
						"boundingRegions": [
							{
								"pageNumber": 1,
								"polygon": [
									2.4315,
									3.7737,
									3.369,
									3.7737,
									3.369,
									4.1091,
									2.4315,
									4.1091
								]
							}
						],
						"spans": [
							{
								"offset": 239,
								"length": 4
							}
						]
					},
					{
						"rowIndex": 1,
						"columnIndex": 2,
						"content": "1",
						"boundingRegions": [
							{
								"pageNumber": 1,
								"polygon": [
									3.369,
									3.7737,
									4.2396,
									3.7737,
									4.2463,
									4.1091,
									3.369,
									4.1091
								]
							}
						],
						"spans": [
							{
								"offset": 244,
								"length": 1
							}
						]
					},
					{
						"rowIndex": 1,
						"columnIndex": 3,
						"content": "5.25",
						"boundingRegions": [
							{
								"pageNumber": 1,
								"polygon": [
									4.2396,
									3.7737,
									7.4941,
									3.767,
									7.4941,
									4.1091,
									4.2463,
									4.1091
								]
							}
						],
						"spans": [
							{
								"offset": 246,
								"length": 4
							}
						]
					},
					{
						"rowIndex": 2,
						"columnIndex": 0,
						"content": "TOTAL",
						"boundingRegions": [
							{
								"pageNumber": 1,
								"polygon": [
									0.9917,
									4.1091,
									2.4315,
									4.1091,
									2.4315,
									4.4311,
									0.9917,
									4.4378
								]
							}
						],
						"spans": [
							{
								"offset": 251,
								"length": 5
							}
						]
					},
					{
						"rowIndex": 2,
						"columnIndex": 1,
						"content": "",
						"boundingRegions": [
							{
								"pageNumber": 1,
								"polygon": [
									2.4315,
									4.1091,
									3.369,
									4.1091,
									3.369,
									4.4311,
									2.4315,
									4.4311
								]
							}
						],
						"spans": []
					},
					{
						"rowIndex": 2,
						"columnIndex": 2,
						"content": "3",
						"boundingRegions": [
							{
								"pageNumber": 1,
								"polygon": [
									3.369,
									4.1091,
									4.2463,
									4.1091,
									4.2463,
									4.4378,
									3.369,
									4.4311
								]
							}
						],
						"spans": [
							{
								"offset": 257,
								"length": 1
							}
						]
					},
					{
						"rowIndex": 2,
						"columnIndex": 3,
						"content": "24.25",
						"boundingRegions": [
							{
								"pageNumber": 1,
								"polygon": [
									4.2463,
									4.1091,
									7.4941,
									4.1091,
									7.4941,
									4.4378,
									4.2463,
									4.4378
								]
							}
						],
						"spans": [
							{
								"offset": 259,
								"length": 5
							}
						]
					}
				],
				"boundingRegions": [
					{
						"pageNumber": 1,
						"polygon": [
							0.9829,
							3.4436,
							7.5129,
							3.4464,
							7.5131,
							4.446,
							0.9822,
							4.443
						]
					}
				],
				"spans": [
					{
						"offset": 213,
						"length": 51
					}
				]
			},
			{
				"rowCount": 2,
				"columnCount": 3,
				"cells": [
					{
						"kind": "columnHeader",
						"rowIndex": 0,
						"columnIndex": 0,
						"content": "CUSTOMER SIGNATURE:",
						"boundingRegions": [
							{
								"pageNumber": 1,
								"polygon": [
									0.9962,
									4.5984,
									2.9622,
									4.5984,
									2.9622,
									4.9189,
									0.9962,
									4.9256
								]
							}
						],
						"spans": [
							{
								"offset": 265,
								"length": 19
							}
						]
					},
					{
						"kind": "columnHeader",
						"rowIndex": 0,
						"columnIndex": 1,
						"content": "",
						"boundingRegions": [
							{
								"pageNumber": 1,
								"polygon": [
									2.9622,
									4.5984,
									4.9952,
									4.5984,
									4.9952,
									4.9189,
									2.9622,
									4.9189
								]
							}
						],
						"spans": []
					},
					{
						"kind": "columnHeader",
						"rowIndex": 0,
						"columnIndex": 2,
						"content": "NAME: Sarah P",
						"boundingRegions": [
							{
								"pageNumber": 1,
								"polygon": [
									4.9952,
									4.5984,
									7.4828,
									4.5984,
									7.4828,
									4.9256,
									4.9952,
									4.9189
								]
							}
						],
						"spans": [
							{
								"offset": 285,
								"length": 13
							}
						]
					},
					{
						"rowIndex": 1,
						"columnIndex": 0,
						"content": "DRIVER SIGNATURE:",
						"boundingRegions": [
							{
								"pageNumber": 1,
								"polygon": [
									0.9962,
									4.9256,
									2.9622,
									4.9189,
									2.9556,
									5.2528,
									0.9895,
									5.2528
								]
							}
						],
						"spans": [
							{
								"offset": 299,
								"length": 17
							}
						]
					},
					{
						"rowIndex": 1,
						"columnIndex": 1,
						"content": "",
						"boundingRegions": [
							{
								"pageNumber": 1,
								"polygon": [
									2.9622,
									4.9189,
									4.9952,
									4.9189,
									4.9952,
									5.2528,
									2.9556,
									5.2528
								]
							}
						],
						"spans": []
					},
					{
						"rowIndex": 1,
						"columnIndex": 2,
						"content": "NAME: James T",
						"boundingRegions": [
							{
								"pageNumber": 1,
								"polygon": [
									4.9952,
									4.9189,
									7.4828,
									4.9256,
									7.4895,
									5.2528,
									4.9952,
									5.2528
								]
							}
						],
						"spans": [
							{
								"offset": 317,
								"length": 13
							}
						]
					}
				],
				"boundingRegions": [
					{
						"pageNumber": 1,
						"polygon": [
							0.9856,
							4.5871,
							7.5099,
							4.5941,
							7.51,
							5.2683,
							0.9847,
							5.2614
						]
					}
				],
				"spans": [
					{
						"offset": 265,
						"length": 65
					}
				]
			},
			{
				"rowCount": 4,
				"columnCount": 3,
				"cells": [
					{
						"rowIndex": 0,
						"columnIndex": 0,
						"content": "Customer:",
						"boundingRegions": [
							{
								"pageNumber": 2,
								"polygon": [
									4.0065,
									1.8524,
									4.8421,
									1.8524,
									4.8421,
									2.0195,
									4.0065,
									2.0195
								]
							}
						],
						"spans": [
							{
								"offset": 373,
								"length": 9
							}
						]
					},
					{
						"rowIndex": 0,
						"columnIndex": 1,
						"columnSpan": 2,
						"content": "Hessel",
						"boundingRegions": [
							{
								"pageNumber": 2,
								"polygon": [
									4.8421,
									1.8524,
									7.4924,
									1.8524,
									7.4924,
									2.0195,
									4.8421,
									2.0195
								]
							}
						],
						"spans": [
							{
								"offset": 383,
								"length": 6
							}
						]
					},
					{
						"rowIndex": 1,
						"columnIndex": 0,
						"content": "Address:",
						"boundingRegions": [
							{
								"pageNumber": 2,
								"polygon": [
									4.0065,
									2.0195,
									4.8421,
									2.0195,
									4.8421,
									2.1962,
									4.0065,
									2.1962
								]
							}
						],
						"spans": [
							{
								"offset": 390,
								"length": 8
							}
						]
					},
					{
						"rowIndex": 1,
						"columnIndex": 1,
						"columnSpan": 2,
						"content": "41 Borough Road, Birmingham, B1 5NB",
						"boundingRegions": [
							{
								"pageNumber": 2,
								"polygon": [
									4.8421,
									2.0195,
									7.4924,
									2.0195,
									7.4924,
									2.1962,
									4.8421,
									2.1962
								]
							}
						],
						"spans": [
							{
								"offset": 399,
								"length": 35
							}
						]
					},
					{
						"rowIndex": 2,
						"columnIndex": 0,
						"content": "Delivery Date:",
						"boundingRegions": [
							{
								"pageNumber": 2,
								"polygon": [
									4.0065,
									2.1962,
									4.8421,
									2.1962,
									4.8421,
									2.5208,
									4.0017,
									2.5208
								]
							}
						],
						"spans": [
							{
								"offset": 435,
								"length": 14
							}
						]
					},
					{
						"rowIndex": 2,
						"columnIndex": 1,
						"columnSpan": 2,
						"content": "6/19/2024",
						"boundingRegions": [
							{
								"pageNumber": 2,
								"polygon": [
									4.8421,
									2.1962,
									7.4924,
									2.1962,
									7.4924,
									2.5208,
									4.8421,
									2.5208
								]
							}
						],
						"spans": [
							{
								"offset": 450,
								"length": 9
							}
						]
					},
					{
						"rowIndex": 3,
						"columnIndex": 0,
						"content": "Invoice #:",
						"boundingRegions": [
							{
								"pageNumber": 2,
								"polygon": [
									4.0017,
									2.5208,
									4.8421,
									2.5208,
									4.8421,
									2.6975,
									4.0017,
									2.6975
								]
							}
						],
						"spans": [
							{
								"offset": 460,
								"length": 10
							}
						]
					},
					{
						"rowIndex": 3,
						"columnIndex": 1,
						"content": "4441423",
						"boundingRegions": [
							{
								"pageNumber": 2,
								"polygon": [
									4.8421,
									2.5208,
									5.6014,
									2.5208,
									5.6062,
									2.6975,
									4.8421,
									2.6975
								]
							}
						],
						"spans": [
							{
								"offset": 471,
								"length": 7
							}
						]
					},
					{
						"rowIndex": 3,
						"columnIndex": 2,
						"content": "Purchase Order: 17211",
						"boundingRegions": [
							{
								"pageNumber": 2,
								"polygon": [
									5.6014,
									2.5208,
									7.4924,
									2.5208,
									7.4972,
									2.6975,
									5.6062,
									2.6975
								]
							}
						],
						"spans": [
							{
								"offset": 479,
								"length": 21
							}
						]
					}
				],
				"boundingRegions": [
					{
						"pageNumber": 2,
						"polygon": [
							3.9995,
							1.8511,
							7.5032,
							1.8516,
							7.5026,
							2.7036,
							3.9986,
							2.7036
						]
					}
				],
				"spans": [
					{
						"offset": 373,
						"length": 127
					}
				]
			},
			{
				"rowCount": 2,
				"columnCount": 3,
				"cells": [
					{
						"rowIndex": 0,
						"columnIndex": 0,
						"content": "",
						"boundingRegions": [
							{
								"pageNumber": 2,
								"polygon": [
									0.9963,
									3.4582,
									2.4351,
									3.4582,
									2.4351,
									3.78,
									0.9963,
									3.78
								]
							}
						],
						"spans": []
					},
					{
						"rowIndex": 0,
						"columnIndex": 1,
						"content": "",
						"boundingRegions": [
							{
								"pageNumber": 2,
								"polygon": [
									2.4351,
									3.4582,
									3.2917,
									3.4515,
									3.2984,
									3.7733,
									2.4351,
									3.78
								]
							}
						],
						"spans": []
					},
					{
						"rowIndex": 0,
						"columnIndex": 2,
						"content": "",
						"boundingRegions": [
							{
								"pageNumber": 2,
								"polygon": [
									3.2917,
									3.4515,
									7.4808,
									3.4515,
									7.4875,
									3.7733,
									3.2984,
									3.7733
								]
							}
						],
						"spans": []
					},
					{
						"rowIndex": 1,
						"columnIndex": 0,
						"content": "TOTAL",
						"boundingRegions": [
							{
								"pageNumber": 2,
								"polygon": [
									0.9963,
									3.78,
									2.4351,
									3.78,
									2.4351,
									4.1017,
									0.9963,
									4.1017
								]
							}
						],
						"spans": [
							{
								"offset": 528,
								"length": 5
							}
						]
					},
					{
						"rowIndex": 1,
						"columnIndex": 1,
						"content": "0",
						"boundingRegions": [
							{
								"pageNumber": 2,
								"polygon": [
									2.4351,
									3.78,
									3.2984,
									3.7733,
									3.3051,
									4.1017,
									2.4351,
									4.1017
								]
							}
						],
						"spans": [
							{
								"offset": 534,
								"length": 1
							}
						]
					},
					{
						"rowIndex": 1,
						"columnIndex": 2,
						"content": "",
						"boundingRegions": [
							{
								"pageNumber": 2,
								"polygon": [
									3.2984,
									3.7733,
									7.4875,
									3.7733,
									7.4942,
									4.1085,
									3.3051,
									4.1017
								]
							}
						],
						"spans": []
					}
				],
				"boundingRegions": [
					{
						"pageNumber": 2,
						"polygon": [
							0.9879,
							3.4466,
							7.5099,
							3.4517,
							7.5111,
							4.1181,
							0.9882,
							4.1132
						]
					}
				],
				"spans": [
					{
						"offset": 528,
						"length": 7
					}
				]
			},
			{
				"rowCount": 2,
				"columnCount": 3,
				"cells": [
					{
						"kind": "columnHeader",
						"rowIndex": 0,
						"columnIndex": 0,
						"content": "CUSTOMER SIGNATURE:",
						"boundingRegions": [
							{
								"pageNumber": 2,
								"polygon": [
									0.9984,
									4.2804,
									3.4025,
									4.2804,
									3.4025,
									4.6009,
									0.9984,
									4.6009
								]
							}
						],
						"spans": [
							{
								"offset": 536,
								"length": 19
							}
						]
					},
					{
						"kind": "columnHeader",
						"rowIndex": 0,
						"columnIndex": 1,
						"content": "",
						"boundingRegions": [
							{
								"pageNumber": 2,
								"polygon": [
									3.4025,
									4.2804,
									4.9896,
									4.2737,
									4.9896,
									4.5943,
									3.4025,
									4.6009
								]
							}
						],
						"spans": []
					},
					{
						"kind": "columnHeader",
						"rowIndex": 0,
						"columnIndex": 2,
						"content": "NAME:",
						"boundingRegions": [
							{
								"pageNumber": 2,
								"polygon": [
									4.9896,
									4.2737,
									7.4941,
									4.2737,
									7.4941,
									4.5943,
									4.9896,
									4.5943
								]
							}
						],
						"spans": [
							{
								"offset": 556,
								"length": 5
							}
						]
					},
					{
						"rowIndex": 1,
						"columnIndex": 0,
						"columnSpan": 2,
						"content": "DRIVER SIGNATURE:",
						"boundingRegions": [
							{
								"pageNumber": 2,
								"polygon": [
									0.9984,
									4.6009,
									4.9896,
									4.5943,
									4.9963,
									4.9081,
									0.9984,
									4.9215
								]
							}
						],
						"spans": [
							{
								"offset": 562,
								"length": 17
							}
						]
					},
					{
						"rowIndex": 1,
						"columnIndex": 2,
						"content": "NAME: James T",
						"boundingRegions": [
							{
								"pageNumber": 2,
								"polygon": [
									4.9896,
									4.5943,
									7.4941,
									4.5943,
									7.4941,
									4.9081,
									4.9963,
									4.9081
								]
							}
						],
						"spans": [
							{
								"offset": 580,
								"length": 13
							}
						]
					}
				],
				"boundingRegions": [
					{
						"pageNumber": 2,
						"polygon": [
							0.985,
							4.2596,
							7.5134,
							4.2669,
							7.5134,
							4.942,
							0.984,
							4.9349
						]
					}
				],
				"spans": [
					{
						"offset": 536,
						"length": 57
					}
				]
			}
		],
		"paragraphs": [
			{
				"spans": [
					{
						"offset": 0,
						"length": 6
					}
				],
				"boundingRegions": [
					{
						"pageNumber": 1,
						"polygon": [
							1.0649,
							1.2031,
							2.0104,
							1.2031,
							2.0104,
							1.4084,
							1.0649,
							1.4084
						]
					}
				],
				"content": "NEXGEN"
			},
			{
				"spans": [
					{
						"offset": 7,
						"length": 26
					}
				],
				"boundingRegions": [
					{
						"pageNumber": 1,
						"polygon": [
							1.0649,
							1.5326,
							2.7033,
							1.5373,
							2.7028,
							1.6949,
							1.0644,
							1.6901
						]
					}
				],
				"content": "Innovation drives progress"
			},
			{
				"spans": [
					{
						"offset": 34,
						"length": 42
					}
				],
				"boundingRegions": [
					{
						"pageNumber": 1,
						"polygon": [
							1.0267,
							3.2274,
							5.2719,
							3.2274,
							5.2719,
							3.3802,
							1.0267,
							3.3802
						]
					}
				],
				"content": "PRODUCT ID UNIT PRICE QUANTITY TOTAL PRICE"
			},
			{
				"spans": [
					{
						"offset": 77,
						"length": 7
					}
				],
				"boundingRegions": [
					{
						"pageNumber": 1,
						"polygon": [
							6.0598,
							1.2222,
							7.416,
							1.2222,
							7.416,
							1.523,
							6.0598,
							1.523
						]
					}
				],
				"role": "title",
				"content": "INVOICE"
			},
			{
				"spans": [
					{
						"offset": 85,
						"length": 9
					}
				],
				"boundingRegions": [
					{
						"pageNumber": 1,
						"polygon": [
							4.0065,
							1.8524,
							4.8421,
							1.8524,
							4.8421,
							2.0195,
							4.0065,
							2.0195
						]
					}
				],
				"content": "Customer:"
			},
			{
				"spans": [
					{
						"offset": 95,
						"length": 6
					}
				],
				"boundingRegions": [
					{
						"pageNumber": 1,
						"polygon": [
							4.8421,
							1.8524,
							7.4924,
							1.8524,
							7.4924,
							2.0195,
							4.8421,
							2.0195
						]
					}
				],
				"content": "Hessel"
			},
			{
				"spans": [
					{
						"offset": 102,
						"length": 8
					}
				],
				"boundingRegions": [
					{
						"pageNumber": 1,
						"polygon": [
							4.0065,
							2.0195,
							4.8421,
							2.0195,
							4.8421,
							2.1962,
							4.0065,
							2.1962
						]
					}
				],
				"content": "Address:"
			},
			{
				"spans": [
					{
						"offset": 111,
						"length": 35
					}
				],
				"boundingRegions": [
					{
						"pageNumber": 1,
						"polygon": [
							4.8421,
							2.0195,
							7.4924,
							2.0195,
							7.4924,
							2.1962,
							4.8421,
							2.1962
						]
					}
				],
				"content": "41 Borough Road, Birmingham, B1 5NB"
			},
			{
				"spans": [
					{
						"offset": 147,
						"length": 14
					}
				],
				"boundingRegions": [
					{
						"pageNumber": 1,
						"polygon": [
							4.0065,
							2.1962,
							4.8421,
							2.1962,
							4.8421,
							2.5208,
							4.0017,
							2.5208
						]
					}
				],
				"content": "Delivery Date:"
			},
			{
				"spans": [
					{
						"offset": 162,
						"length": 9
					}
				],
				"boundingRegions": [
					{
						"pageNumber": 1,
						"polygon": [
							4.8421,
							2.1962,
							7.4924,
							2.1962,
							7.4924,
							2.5208,
							4.8421,
							2.5208
						]
					}
				],
				"content": "6/19/2024"
			},
			{
				"spans": [
					{
						"offset": 172,
						"length": 10
					}
				],
				"boundingRegions": [
					{
						"pageNumber": 1,
						"polygon": [
							4.0017,
							2.5208,
							4.8421,
							2.5208,
							4.8421,
							2.6975,
							4.0017,
							2.6975
						]
					}
				],
				"content": "Invoice #:"
			},
			{
				"spans": [
					{
						"offset": 183,
						"length": 7
					}
				],
				"boundingRegions": [
					{
						"pageNumber": 1,
						"polygon": [
							4.8421,
							2.5208,
							5.6014,
							2.5208,
							5.6062,
							2.6975,
							4.8421,
							2.6975
						]
					}
				],
				"content": "4441423"
			},
			{
				"spans": [
					{
						"offset": 191,
						"length": 21
					}
				],
				"boundingRegions": [
					{
						"pageNumber": 1,
						"polygon": [
							5.6014,
							2.5208,
							7.4924,
							2.5208,
							7.4972,
							2.6975,
							5.6062,
							2.6975
						]
					}
				],
				"content": "Purchase Order: 17211"
			},
			{
				"spans": [
					{
						"offset": 213,
						"length": 5
					}
				],
				"boundingRegions": [
					{
						"pageNumber": 1,
						"polygon": [
							0.9984,
							3.4517,
							2.4315,
							3.4517,
							2.4315,
							3.7737,
							0.9917,
							3.7737
						]
					}
				],
				"content": "JB508"
			},
			{
				"spans": [
					{
						"offset": 219,
						"length": 4
					}
				],
				"boundingRegions": [
					{
						"pageNumber": 1,
						"polygon": [
							2.4315,
							3.4517,
							3.3757,
							3.4517,
							3.369,
							3.7737,
							2.4315,
							3.7737
						]
					}
				],
				"content": "9.50"
			},
			{
				"spans": [
					{
						"offset": 224,
						"length": 1
					}
				],
				"boundingRegions": [
					{
						"pageNumber": 1,
						"polygon": [
							3.3757,
							3.4517,
							4.2329,
							3.4517,
							4.2396,
							3.7737,
							3.369,
							3.7737
						]
					}
				],
				"content": "2"
			},
			{
				"spans": [
					{
						"offset": 226,
						"length": 5
					}
				],
				"boundingRegions": [
					{
						"pageNumber": 1,
						"polygon": [
							4.2329,
							3.4517,
							7.4941,
							3.4517,
							7.4941,
							3.767,
							4.2396,
							3.7737
						]
					}
				],
				"content": "19.00"
			},
			{
				"spans": [
					{
						"offset": 232,
						"length": 6
					}
				],
				"boundingRegions": [
					{
						"pageNumber": 1,
						"polygon": [
							0.9917,
							3.7737,
							2.4315,
							3.7737,
							2.4315,
							4.1091,
							0.9917,
							4.1091
						]
					}
				],
				"content": "PL-14X"
			},
			{
				"spans": [
					{
						"offset": 239,
						"length": 4
					}
				],
				"boundingRegions": [
					{
						"pageNumber": 1,
						"polygon": [
							2.4315,
							3.7737,
							3.369,
							3.7737,
							3.369,
							4.1091,
							2.4315,
							4.1091
						]
					}
				],
				"content": "5.25"
			},
			{
				"spans": [
					{
						"offset": 244,
						"length": 1
					}
				],
				"boundingRegions": [
					{
						"pageNumber": 1,
						"polygon": [
							3.369,
							3.7737,
							4.2396,
							3.7737,
							4.2463,
							4.1091,
							3.369,
							4.1091
						]
					}
				],
				"content": "1"
			},
			{
				"spans": [
					{
						"offset": 246,
						"length": 4
					}
				],
				"boundingRegions": [
					{
						"pageNumber": 1,
						"polygon": [
							4.2396,
							3.7737,
							7.4941,
							3.767,
							7.4941,
							4.1091,
							4.2463,
							4.1091
						]
					}
				],
				"content": "5.25"
			},
			{
				"spans": [
					{
						"offset": 251,
						"length": 5
					}
				],
				"boundingRegions": [
					{
						"pageNumber": 1,
						"polygon": [
							0.9917,
							4.1091,
							2.4315,
							4.1091,
							2.4315,
							4.4311,
							0.9917,
							4.4378
						]
					}
				],
				"content": "TOTAL"
			},
			{
				"spans": [
					{
						"offset": 257,
						"length": 1
					}
				],
				"boundingRegions": [
					{
						"pageNumber": 1,
						"polygon": [
							3.369,
							4.1091,
							4.2463,
							4.1091,
							4.2463,
							4.4378,
							3.369,
							4.4311
						]
					}
				],
				"content": "3"
			},
			{
				"spans": [
					{
						"offset": 259,
						"length": 5
					}
				],
				"boundingRegions": [
					{
						"pageNumber": 1,
						"polygon": [
							4.2463,
							4.1091,
							7.4941,
							4.1091,
							7.4941,
							4.4378,
							4.2463,
							4.4378
						]
					}
				],
				"content": "24.25"
			},
			{
				"spans": [
					{
						"offset": 265,
						"length": 19
					}
				],
				"boundingRegions": [
					{
						"pageNumber": 1,
						"polygon": [
							0.9962,
							4.5984,
							2.9622,
							4.5984,
							2.9622,
							4.9189,
							0.9962,
							4.9256
						]
					}
				],
				"content": "CUSTOMER SIGNATURE:"
			},
			{
				"spans": [
					{
						"offset": 285,
						"length": 13
					}
				],
				"boundingRegions": [
					{
						"pageNumber": 1,
						"polygon": [
							4.9952,
							4.5984,
							7.4828,
							4.5984,
							7.4828,
							4.9256,
							4.9952,
							4.9189
						]
					}
				],
				"content": "NAME: Sarah P"
			},
			{
				"spans": [
					{
						"offset": 299,
						"length": 17
					}
				],
				"boundingRegions": [
					{
						"pageNumber": 1,
						"polygon": [
							0.9962,
							4.9256,
							2.9622,
							4.9189,
							2.9556,
							5.2528,
							0.9895,
							5.2528
						]
					}
				],
				"content": "DRIVER SIGNATURE:"
			},
			{
				"spans": [
					{
						"offset": 317,
						"length": 13
					}
				],
				"boundingRegions": [
					{
						"pageNumber": 1,
						"polygon": [
							4.9952,
							4.9189,
							7.4828,
							4.9256,
							7.4895,
							5.2528,
							4.9952,
							5.2528
						]
					}
				],
				"content": "NAME: James T"
			},
			{
				"spans": [
					{
						"offset": 331,
						"length": 6
					}
				],
				"boundingRegions": [
					{
						"pageNumber": 2,
						"polygon": [
							1.0649,
							1.2031,
							2.0104,
							1.2031,
							2.0104,
							1.4084,
							1.0649,
							1.4084
						]
					}
				],
				"content": "NEXGEN"
			},
			{
				"spans": [
					{
						"offset": 338,
						"length": 26
					}
				],
				"boundingRegions": [
					{
						"pageNumber": 2,
						"polygon": [
							1.0649,
							1.5326,
							2.7033,
							1.5373,
							2.7028,
							1.6949,
							1.0644,
							1.6901
						]
					}
				],
				"content": "Innovation drives progress"
			},
			{
				"spans": [
					{
						"offset": 365,
						"length": 7
					}
				],
				"boundingRegions": [
					{
						"pageNumber": 2,
						"polygon": [
							5.8765,
							1.2318,
							7.4046,
							1.2222,
							7.4065,
							1.5135,
							5.8784,
							1.523
						]
					}
				],
				"content": "RETURNS"
			},
			{
				"spans": [
					{
						"offset": 373,
						"length": 9
					}
				],
				"boundingRegions": [
					{
						"pageNumber": 2,
						"polygon": [
							4.0065,
							1.8524,
							4.8421,
							1.8524,
							4.8421,
							2.0195,
							4.0065,
							2.0195
						]
					}
				],
				"content": "Customer:"
			},
			{
				"spans": [
					{
						"offset": 383,
						"length": 6
					}
				],
				"boundingRegions": [
					{
						"pageNumber": 2,
						"polygon": [
							4.8421,
							1.8524,
							7.4924,
							1.8524,
							7.4924,
							2.0195,
							4.8421,
							2.0195
						]
					}
				],
				"content": "Hessel"
			},
			{
				"spans": [
					{
						"offset": 390,
						"length": 8
					}
				],
				"boundingRegions": [
					{
						"pageNumber": 2,
						"polygon": [
							4.0065,
							2.0195,
							4.8421,
							2.0195,
							4.8421,
							2.1962,
							4.0065,
							2.1962
						]
					}
				],
				"content": "Address:"
			},
			{
				"spans": [
					{
						"offset": 399,
						"length": 35
					}
				],
				"boundingRegions": [
					{
						"pageNumber": 2,
						"polygon": [
							4.8421,
							2.0195,
							7.4924,
							2.0195,
							7.4924,
							2.1962,
							4.8421,
							2.1962
						]
					}
				],
				"content": "41 Borough Road, Birmingham, B1 5NB"
			},
			{
				"spans": [
					{
						"offset": 435,
						"length": 14
					}
				],
				"boundingRegions": [
					{
						"pageNumber": 2,
						"polygon": [
							4.0065,
							2.1962,
							4.8421,
							2.1962,
							4.8421,
							2.5208,
							4.0017,
							2.5208
						]
					}
				],
				"content": "Delivery Date:"
			},
			{
				"spans": [
					{
						"offset": 450,
						"length": 9
					}
				],
				"boundingRegions": [
					{
						"pageNumber": 2,
						"polygon": [
							4.8421,
							2.1962,
							7.4924,
							2.1962,
							7.4924,
							2.5208,
							4.8421,
							2.5208
						]
					}
				],
				"content": "6/19/2024"
			},
			{
				"spans": [
					{
						"offset": 460,
						"length": 10
					}
				],
				"boundingRegions": [
					{
						"pageNumber": 2,
						"polygon": [
							4.0017,
							2.5208,
							4.8421,
							2.5208,
							4.8421,
							2.6975,
							4.0017,
							2.6975
						]
					}
				],
				"content": "Invoice #:"
			},
			{
				"spans": [
					{
						"offset": 471,
						"length": 7
					}
				],
				"boundingRegions": [
					{
						"pageNumber": 2,
						"polygon": [
							4.8421,
							2.5208,
							5.6014,
							2.5208,
							5.6062,
							2.6975,
							4.8421,
							2.6975
						]
					}
				],
				"content": "4441423"
			},
			{
				"spans": [
					{
						"offset": 479,
						"length": 21
					}
				],
				"boundingRegions": [
					{
						"pageNumber": 2,
						"polygon": [
							5.6014,
							2.5208,
							7.4924,
							2.5208,
							7.4972,
							2.6975,
							5.6062,
							2.6975
						]
					}
				],
				"content": "Purchase Order: 17211"
			},
			{
				"spans": [
					{
						"offset": 501,
						"length": 26
					}
				],
				"boundingRegions": [
					{
						"pageNumber": 2,
						"polygon": [
							1.0267,
							3.2274,
							3.973,
							3.2274,
							3.973,
							3.3898,
							1.0267,
							3.3898
						]
					}
				],
				"role": "sectionHeading",
				"content": "PRODUCT ID QUANTITY REASON"
			},
			{
				"spans": [
					{
						"offset": 528,
						"length": 5
					}
				],
				"boundingRegions": [
					{
						"pageNumber": 2,
						"polygon": [
							0.9963,
							3.78,
							2.4351,
							3.78,
							2.4351,
							4.1017,
							0.9963,
							4.1017
						]
					}
				],
				"content": "TOTAL"
			},
			{
				"spans": [
					{
						"offset": 534,
						"length": 1
					}
				],
				"boundingRegions": [
					{
						"pageNumber": 2,
						"polygon": [
							2.4351,
							3.78,
							3.2984,
							3.7733,
							3.3051,
							4.1017,
							2.4351,
							4.1017
						]
					}
				],
				"content": "0"
			},
			{
				"spans": [
					{
						"offset": 536,
						"length": 19
					}
				],
				"boundingRegions": [
					{
						"pageNumber": 2,
						"polygon": [
							0.9984,
							4.2804,
							3.4025,
							4.2804,
							3.4025,
							4.6009,
							0.9984,
							4.6009
						]
					}
				],
				"content": "CUSTOMER SIGNATURE:"
			},
			{
				"spans": [
					{
						"offset": 556,
						"length": 5
					}
				],
				"boundingRegions": [
					{
						"pageNumber": 2,
						"polygon": [
							4.9896,
							4.2737,
							7.4941,
							4.2737,
							7.4941,
							4.5943,
							4.9896,
							4.5943
						]
					}
				],
				"content": "NAME:"
			},
			{
				"spans": [
					{
						"offset": 562,
						"length": 17
					}
				],
				"boundingRegions": [
					{
						"pageNumber": 2,
						"polygon": [
							0.9984,
							4.6009,
							4.9896,
							4.5943,
							4.9963,
							4.9081,
							0.9984,
							4.9215
						]
					}
				],
				"content": "DRIVER SIGNATURE:"
			},
			{
				"spans": [
					{
						"offset": 580,
						"length": 13
					}
				],
				"boundingRegions": [
					{
						"pageNumber": 2,
						"polygon": [
							4.9896,
							4.5943,
							7.4941,
							4.5943,
							7.4941,
							4.9081,
							4.9963,
							4.9081
						]
					}
				],
				"content": "NAME: James T"
			}
		],
		"styles": [
			{
				"confidence": 0.1,
				"spans": [
					{
						"offset": 244,
						"length": 1
					}
				],
				"isHandwritten": true
			}
		]
	}
}